flake8parser/__init__.py
flake8parser/test_flake8parser.py
flake8parser-0.1.1.dist-info/METADATA
flake8parser-0.1.1.dist-info/WHEEL
flake8parser-0.1.1.dist-info/top_level.txt
flake8parser-0.1.1.dist-info/RECORD
