Metadata-Version: 2.1
Name: flake8parser
Version: 0.1.1
Summary: A public python API for flake8 created by parsing the command line output.
Home-page: https://github.com/newAM/flake8parser
Author: Alex M.
Author-email: 7845120+newAM@users.noreply.github.com
License: MIT
Platform: UNKNOWN
Classifier: Programming Language :: Python :: 3.6
Classifier: Programming Language :: Python :: 3.7
Classifier: Programming Language :: Python :: 3.8
Requires-Python: >=3.6
Requires-Dist: flake8 (>=3.8.2)
